pypkgs_yaz/__init__.py
pypkgs_yaz/pypkgs_yaz.py
pypkgs_yaz-0.1.0.dist-info/LICENSE
pypkgs_yaz-0.1.0.dist-info/WHEEL
pypkgs_yaz-0.1.0.dist-info/METADATA
pypkgs_yaz-0.1.0.dist-info/RECORD
